{
  "slug": "balerion",
  "domain": "balerion.ai",
  "url": "https://balerion.ai",
  "product_name": "Balerion",
  "summary": "AI loan-intelligence platform for mortgage origination.",
  "editor_note": "The smart move is starting where mortgage files actually break: income math, missing documents, NSF flags, and Fannie/Freddie overlays. Balerion Loan Intelligence is already used by FM Home Loans, a lender managing $2B+ in loan volume, and embeds into existing origination workflows. Unlike point AI tools, it wants to reason across the whole loan file. The risk is enterprise pilots turning into custom services.",
  "editor_rating": 4,
  "why_featured": "$2B lender using Loan Intelligence",
  "product_type": "Fintech",
  "region": "US",
  "tags": "mortgage,ai agents,fintech,loan origination",
  "investors": "Kleiner Perkins",
  "links": {
    "twitter": "https://x.com/BalerionAI",
    "linkedin": "https://www.linkedin.com/company/balerion-ai/"
  },
  "is_featured": false,
  "funding": [
    {
      "amount": "$6M",
      "stage": "Seed",
      "lead_investor": "Kleiner Perkins",
      "date": "2026-04-16",
      "source_url": "https://balerion.ai/press",
      "source_name": "Balerion"
    }
  ],
  "research": {
    "verified_at": "2026-05-26",
    "sources": [
      {
        "id": "official_site",
        "label": "Official product site",
        "url": "https://balerion.ai",
        "type": "official"
      },
      {
        "id": "funding_1",
        "label": "Balerion",
        "url": "https://balerion.ai/press",
        "type": "funding"
      }
    ],
    "product_evidence": [
      {
        "claim": "Official product positioning describes Balerion: AI loan-intelligence platform for mortgage origination.",
        "source_ids": [
          "official_site"
        ]
      },
      {
        "claim": "Balerion Loan Intelligence is already used by FM Home Loans, a lender managing $2B+ in loan volume, and embeds into existing origination workflows.",
        "source_ids": [
          "official_site"
        ]
      }
    ],
    "market_context": {
      "primary_user": "Finance, banking, or payments teams evaluating regulated transaction workflows.",
      "category": "Fintech",
      "differentiation": "$2B lender using Loan Intelligence",
      "why_now": "Recent source-backed funding and public product evidence make mortgage, ai agents, fintech worth tracking."
    },
    "risks": [
      {
        "claim": "The risk is enterprise pilots turning into custom services.",
        "basis": "VentureDex editorial assessment based on official product evidence and funding-source review."
      }
    ]
  }
}
